odoo/addons/sale_order_invoice_amount/README.rst
odoo/addons/sale_order_invoice_amount/__init__.py
odoo/addons/sale_order_invoice_amount/__manifest__.py
odoo/addons/sale_order_invoice_amount/i18n/es.po
odoo/addons/sale_order_invoice_amount/i18n/fr.po
odoo/addons/sale_order_invoice_amount/i18n/it.po
odoo/addons/sale_order_invoice_amount/i18n/sale_order_invoice_amount.pot
odoo/addons/sale_order_invoice_amount/migrations/17.0.1.0.0/post-migration.py
odoo/addons/sale_order_invoice_amount/migrations/17.0.1.0.0/pre-migration.py
odoo/addons/sale_order_invoice_amount/models/__init__.py
odoo/addons/sale_order_invoice_amount/models/res_company.py
odoo/addons/sale_order_invoice_amount/models/sale_order.py
odoo/addons/sale_order_invoice_amount/models/sale_order_config_settings.py
odoo/addons/sale_order_invoice_amount/readme/CONTRIBUTORS.md
odoo/addons/sale_order_invoice_amount/readme/DESCRIPTION.md
odoo/addons/sale_order_invoice_amount/static/description/icon.png
odoo/addons/sale_order_invoice_amount/static/description/index.html
odoo/addons/sale_order_invoice_amount/static/src/xml/tax_totals.xml
odoo/addons/sale_order_invoice_amount/tests/__init__.py
odoo/addons/sale_order_invoice_amount/tests/test_sale_order_invoice_amount.py
odoo/addons/sale_order_invoice_amount/views/sale_order_config_settings.xml
odoo/addons/sale_order_invoice_amount/views/sale_order_view.xml
odoo_addon_sale_order_invoice_amount-17.0.1.0.1.dist-info/METADATA
odoo_addon_sale_order_invoice_amount-17.0.1.0.1.dist-info/WHEEL
odoo_addon_sale_order_invoice_amount-17.0.1.0.1.dist-info/top_level.txt
odoo_addon_sale_order_invoice_amount-17.0.1.0.1.dist-info/RECORD
