Metadata-Version: 2.1
Name: odoo-addon-sale_order_invoice_amount
Version: 17.0.1.0.1
Requires-Python: >=3.10
Requires-Dist: odoo>=17.0a,<17.1dev
Summary: Improves Sales Order invoiced/to invoice amount calculation based on product quantities when the company setting is enabled.
Home-page: https://github.com/OCA/sale-workflow
License: LGPL-3
Author: ForgeFlow, Odoo Community Association (OCA)
Author-email: support@odoo-community.org
Classifier: Programming Language :: Python
Classifier: Framework :: Odoo
Classifier: Framework :: Odoo :: 17.0
Classifier: License :: OSI Approved :: GNU Lesser General Public License v3 (LGPLv3)
